node_exporter/__init__.py
node_exporter/__main__.py
node_exporter/node_exporter.py
node_exporter/collector/__init__.py
node_exporter/collector/ccontroller.py
node_exporter/collector/collector.py
node_exporter/collector/cpu.py
node_exporter/collector/diskstats.py
node_exporter/collector/filesystem.py
node_exporter/collector/loadavg.py
node_exporter/collector/meminfo.py
node_exporter/collector/namespace.py
node_exporter/collector/stat.py
node_exporter-0.3.5.dist-info/LICENSE
node_exporter-0.3.5.dist-info/METADATA
node_exporter-0.3.5.dist-info/WHEEL
node_exporter-0.3.5.dist-info/top_level.txt
node_exporter-0.3.5.dist-info/RECORD
