Metadata-Version: 2.1
Name: node-exporter
Version: 0.3.5
Summary: UNKNOWN
Home-page: UNKNOWN
Author: shinhwagk
Author-email: shinhwagk@outlook.com
License: UNKNOWN
Platform: UNKNOWN
Requires-Dist: prometheus-client
